brender/__init__.py
brender-0.1.1.dist-info/METADATA
brender-0.1.1.dist-info/WHEEL
brender-0.1.1.dist-info/licenses/LICENSE
brender-0.1.1.dist-info/RECORD
