Metadata-Version: 2.4
Name: brender
Version: 0.1.1
Summary: Blender render helper
License-File: LICENSE
Requires-Python: >=3.10
